croissance/__init__.py
croissance/main.py
croissance/estimation/__init__.py
croissance/estimation/outliers.py
croissance/estimation/ranking.py
croissance/estimation/regression.py
croissance/estimation/util.py
croissance/estimation/smoothing/__init__.py
croissance/estimation/smoothing/segments.py
croissance/figures/__init__.py
croissance/figures/plot.py
croissance/figures/writer.py
croissance/formats/__init__.py
croissance/formats/input.py
croissance/formats/output.py
tests/__init__.py
tests/api_test.py
tests/estimation/__init__.py
tests/estimation/main_test.py
tests/estimation/util_test.py
croissance-1.2.0.dist-info/LICENSE
croissance-1.2.0.dist-info/METADATA
croissance-1.2.0.dist-info/WHEEL
croissance-1.2.0.dist-info/entry_points.txt
croissance-1.2.0.dist-info/top_level.txt
croissance-1.2.0.dist-info/RECORD
