Metadata-Version: 2.1
Name: croissance
Version: 1.2.0
Summary: A tool for estimating growth rates in growth curves.
Home-page: https://github.com/biosustain/croissance
Author: Lars Schöning
Author-email: lays@biosustain.dtu.dk
License: Apache License Version 2.0
Platform: UNKNOWN
Classifier: Development Status :: 5 - Production/Stable
Classifier: Topic :: Utilities
Classifier: Intended Audience :: Science/Research
Classifier: Programming Language :: Python :: 3
Classifier: Programming Language :: Python :: 3.6
Classifier: License :: OSI Approved :: Apache Software License
License-File: LICENSE
Requires-Dist: coloredlogs (>=14.0.0)
Requires-Dist: matplotlib (>=1.4.3)
Requires-Dist: numpy (>=1.9.1)
Requires-Dist: pandas (>=0.18.0)
Requires-Dist: scipy (>=0.14.0)
